{
  "schema_version": 1,
  "release": "v0.2.1-alpha",
  "package_name": "unlimited-skills",
  "package_version": "0.2.1",
  "git": {
    "repository": "https://github.com/AI4sale/unlimited-skills",
    "sha": "672929b3a237ba99516bee86692a1bc112d9c642",
    "tag": "v0.2.1-alpha",
    "tag_status": "pending_release_owner_approval"
  },
  "required_prs": {
    "private_registry": [
      {
        "number": 2,
        "repository": "AI4sale/unlimited-skills-registry",
        "title": "signed registry manifests",
        "required_before_public_tag": true
      }
    ],
    "public": [
      {
        "number": 13,
        "title": "v0.2.1-alpha Local Skill Hub runtime integration"
      },
      {
        "number": 14,
        "title": "remote-first router installers"
      },
      {
        "number": 15,
        "title": "capability-aware local install plans"
      },
      {
        "number": 16,
        "title": "required signed hosted manifest verification"
      },
      {
        "number": 17,
        "title": "v0.2.1-alpha CI and merge gate"
      },
      {
        "number": 18,
        "title": "trust key bootstrap and rotation"
      },
      {
        "number": 19,
        "title": "hub client lifecycle, quota, audit, and metrics"
      }
    ],
    "finalization_branch": "release/v0.2.1-alpha-finalization"
  },
  "public_trusted_manifest_keys": [
    {
      "key_id": "registry-alpha-2026-06",
      "algorithm": "ed25519",
      "source": "bundled",
      "scopes": [
        "hub-allowlist",
        "catalog-updates",
        "enhancement-manifest",
        "team-sync-manifest"
      ],
      "registry_origins": [
        "https://unlimited.ai4.sale"
      ]
    }
  ],
  "private_registry_signed_manifest_key_reference": {
    "key_id": "registry-alpha-2026-06",
    "repository": "AI4sale/unlimited-skills-registry",
    "artifact": "signed hosted manifests generated by private registry PR #2",
    "private_key_in_public_repo": false
  },
  "feature_scope": [
    "Local Skill Hub runtime",
    "hub token enforcement",
    "remote hub client",
    "allowlist bootstrap",
    "capability-aware local install plans",
    "required signed hosted manifest verification",
    "trusted key bootstrap, origin pinning, and local revocation",
    "client lifecycle, quota, audit, and metrics",
    "release CI and smoke coverage"
  ],
  "distribution_policy": {
    "full_catalog_distribution": false,
    "hub_distribution_mode": "allowlist_only",
    "hosted_query_forwarding": false,
    "hub_executes_skills": false,
    "local_install_plan_skills": "metadata_resolution_only_until_client_capability_checks_are_complete"
  },
  "registration_boundary": {
    "unregistered_public_core_commands": [
      "search",
      "list",
      "view",
      "where",
      "use",
      "feedback",
      "reindex",
      "vector-reindex",
      "serve",
      "adapt",
      "adapt-one",
      "adapt-next",
      "apply-adaptation",
      "sync-native",
      "self-update check",
      "self-update apply",
      "agent installers",
      "migration scripts"
    ],
    "registration_gated_commands": [
      "catalog list",
      "updates check",
      "updates apply",
      "community list/search/preview/install/submit/status",
      "enhance download/run",
      "team create/join/sync/admin commands",
      "hub serve",
      "hub sync",
      "hub client/token management"
    ]
  },
  "security_boundary": {
    "hosted_remote_manifests_require_valid_signatures": true,
    "manifest_signature_algorithm": "ed25519",
    "archive_bytes_verified_by_sha256": true,
    "archive_bytes_cryptographically_signed": false,
    "zip_safe_extraction_required": true,
    "private_signing_keys_shipped": false,
    "production_hosted_calls_in_tests": false
  },
  "ci": {
    "github_actions_required": true,
    "run_ids": [],
    "run_ids_status": "pending_until_finalization_pr_checks_exist"
  },
  "required_test_commands": [
    "python -m pytest tests -q",
    "python scripts/run-v0.2x-smoke-tests.py",
    "python scripts/verify-v0.2.1-alpha-release.py",
    "python scripts/run-v0.2.1-alpha-fresh-install-smoke.py",
    "python scripts/run-v0.2.1-alpha-upgrade-smoke.py",
    "python -m compileall -q unlimited_skills scripts tests",
    "git diff --check"
  ],
  "known_limitations": [
    "Developer preview, not a production SLA.",
    "Hosted registry access is early-access and registration-gated.",
    "Full catalog distribution remains disabled.",
    "Local Skill Hub is allowlist-only alpha.",
    "Archive bytes are SHA256-verified and safely extracted, not archive-byte signed.",
    "PyPI is not the v0.2.x distribution path.",
    "Enterprise Skill Lock is planned, not implemented."
  ],
  "release_owner_actions": [
    "Merge private registry PR #2.",
    "Merge public PR #13 through PR #19 in order.",
    "Merge this finalization PR after evidence is reviewed.",
    "Create tag v0.2.1-alpha only after release-owner approval.",
    "Create a GitHub prerelease with docs/releases/v0.2.1-alpha.md as the source notes."
  ]
}
